[
  {
    "text": "Windows",
    "label": "LOC"
  },
  {
    "text": "OfficeEducation Details",
    "label": "PERSON"
  },
  {
    "text": "Guwahati, Assam University Law College",
    "label": "ORG"
  },
  {
    "text": "Guwahati University",
    "label": "ORG"
  },
  {
    "text": "the Gauhati High Court",
    "label": "ORG"
  },
  {
    "text": "Statutory Bodies",
    "label": "ORG"
  },
  {
    "text": "Guwahati",
    "label": "GPE"
  },
  {
    "text": "2008",
    "label": "DATE"
  },
  {
    "text": "Civil, Criminal",
    "label": "ORG"
  },
  {
    "text": "Civil",
    "label": "GPE"
  },
  {
    "text": "Criminal Matters",
    "label": "ORG"
  },
  {
    "text": "District & Sessions",
    "label": "ORG"
  },
  {
    "text": "Court",
    "label": "PERSON"
  },
  {
    "text": "Court",
    "label": "PERSON"
  },
  {
    "text": "C.J.M. Court",
    "label": "ORG"
  },
  {
    "text": "Consumer Forum &",
    "label": "ORG"
  },
  {
    "text": "the High Court",
    "label": "ORG"
  },
  {
    "text": "Working as Executive (Legal",
    "label": "ORG"
  },
  {
    "text": "Hindustan Paper Corporation Limited",
    "label": "ORG"
  },
  {
    "text": "India Enterprise",
    "label": "ORG"
  },
  {
    "text": "Nagaon Paper Mill",
    "label": "PERSON"
  },
  {
    "text": "Jan '2012",
    "label": "DATE"
  },
  {
    "text": "HPC LTD",
    "label": "ORG"
  },
  {
    "text": "Nagaon Paper Mill",
    "label": "ORG"
  },
  {
    "text": "Cachar Paper Mill",
    "label": "ORG"
  },
  {
    "text": "Nagaland Pulp and Paper Corporation Ltd.",
    "label": "ORG"
  },
  {
    "text": "Corporation",
    "label": "ORG"
  }
]