[
  {
    "text": "February 2006 to February 2006",
    "label": "DATE"
  },
  {
    "text": "Excel",
    "label": "PRODUCT"
  },
  {
    "text": "CAG",
    "label": "ORG"
  },
  {
    "text": "Working on Excel Macro",
    "label": "ORG"
  },
  {
    "text": "Create Innovative Report \n\nWorking on",
    "label": "ORG"
  },
  {
    "text": "BD Fund",
    "label": "ORG"
  },
  {
    "text": "GEO Working on Investors Corporate Meeting",
    "label": "ORG"
  },
  {
    "text": "Corporate Block & Fund Interest",
    "label": "ORG"
  },
  {
    "text": "Maintain Daily MIS",
    "label": "ORG"
  },
  {
    "text": "MIS & ATM",
    "label": "ORG"
  },
  {
    "text": "Maintain",
    "label": "ORG"
  },
  {
    "text": "BANK CASH DEPARTMENT",
    "label": "ORG"
  },
  {
    "text": "14",
    "label": "CARDINAL"
  },
  {
    "text": "Maintain Daily MIS",
    "label": "ORG"
  },
  {
    "text": "Maintain",
    "label": "ORG"
  }
]